setup.py
hxlxalgos/__init__.py
hxlxalgos/cfg.py
hxlxalgos/fantasy.py
hxlxalgos/algos/__init__.py
hxlxalgos/algos/blur_detect.py
hxlxalgos/algos/classification.py
hxlxalgos/algos/detection.py
hxlxalgos/algos/face_align.py
hxlxalgos/algos/face_front_level.py
hxlxalgos/algos/face_landmark.py
hxlxalgos/algos/face_recg.py
hxlxalgos/algos/pose_estimation.py
hxlxalgos/core/__init__.py
hxlxalgos/core/trt_exec.py
hxlxalgos/external/__init__.py
hxlxalgos/external/nms.c
hxlxalgos/external/nms.pyx
hxlxalgos/utils/__init__.py
hxlxalgos/utils/al_util.py
hxlxalgos/utils/coco_util.py
hxlxalgos/utils/common.py
hxlxalgos/utils/intersect.py
hxlxalgos/utils/view_util.py
hxlxalgotrt.egg-info/PKG-INFO
hxlxalgotrt.egg-info/SOURCES.txt
hxlxalgotrt.egg-info/dependency_links.txt
hxlxalgotrt.egg-info/requires.txt
hxlxalgotrt.egg-info/top_level.txt