Metadata-Version: 1.0
Name: hxlxalgotrt
Version: 0.0.3
Summary: Algorithms apis by hxlx.
Home-page: UNKNOWN
Author: hxlx
Author-email: wenlong.hu@ai-baby.com
License: MIT
Keywords: computer vision,deep learning,person detection,face recognition
Platform: UNKNOWN
